GooseTypes-0.1.1.dist-info/METADATA
GooseTypes-0.1.1.dist-info/entry_points.txt
GooseTypes-0.1.1.dist-info/RECORD
GooseTypes-0.1.1.dist-info/top_level.txt
GooseTypes-0.1.1.dist-info/namespace_packages.txt
GooseTypes-0.1.1.dist-info/WHEEL
GooseTypes-0.1.1.dist-info/metadata.json
GooseTypes-0.1.1.dist-info/DESCRIPTION.rst
goosetypes/_core.py
goosetypes/_re.py
goosetypes/_string.py
goosetypes/__init__.py
goosetypes/_num.py
goosetypes/_misc.py
