Metadata-Version: 2.0
Name: GooseTypes
Version: 0.1.1
Summary: Goose Types
Home-page: UNKNOWN
Author: Ivan D Vasin
Author-email: nisavid@gmail.com
License: GNU LESSER GENERAL PUBLIC LICENSE
Requires-Dist: spruce-types
